setup.py
Define_It/__init__.py
Define_It.egg-info/PKG-INFO
Define_It.egg-info/SOURCES.txt
Define_It.egg-info/dependency_links.txt
Define_It.egg-info/not-zip-safe
Define_It.egg-info/requires.txt
Define_It.egg-info/top_level.txt