Metadata-Version: 1.1
Name: Define-It
Version: 2.0.0
Summary: Responds to mentions and keyword "define" with a definition of the word/phrase
Home-page: https://github.com/Spedwards/RedditBots/tree/master/Define_It
Author: Spedwards
Author-email: improbablepuzzle@gmail.com
License: MIT
Platform: UNKNOWN
Classifier: Development Status :: 5 - Production/Stable
Classifier: Environment :: Console
Classifier: Intended Audience :: Developers
Classifier: License :: OSI Approved :: MIT License
Classifier: Natural Language :: English
Classifier: Operating System :: OS Independent
Classifier: Programming Language :: Python :: 3
Classifier: Programming Language :: Python :: 3.4
Classifier: Topic :: Internet
Classifier: Topic :: Software Development :: Libraries
Classifier: Topic :: Software Development :: Libraries :: Python Modules
